pptweaver/__init__.py
pptweaver/cli.py
pptweaver/converter.py
pptweaver/elements/base_processor.py
pptweaver/elements/foreign_object_processor.py
pptweaver/elements/image_processor.py
pptweaver/elements/line_processor.py
pptweaver/elements/oval_processor.py
pptweaver/elements/path_processor.py
pptweaver/elements/polygon_processor.py
pptweaver/elements/rect_processor.py
pptweaver/elements/text_processor.py
pptweaver-0.1.0.dist-info/METADATA
pptweaver-0.1.0.dist-info/WHEEL
pptweaver-0.1.0.dist-info/entry_points.txt
pptweaver-0.1.0.dist-info/top_level.txt
pptweaver-0.1.0.dist-info/RECORD
