Metadata-Version: 2.4
Name: pptweaver
Version: 0.1.0
Summary: An innovative tool to weave your web content into editable PowerPoint presentations.
Author-email: Your Name <youremail@example.com>
Project-URL: Homepage, https://github.com/yourusername/pptweaver
Project-URL: Bug Tracker, https://github.com/yourusername/pptweaver/issues
Classifier: Programming Language :: Python :: 3
Classifier: License :: OSI Approved :: MIT License
Classifier: Operating System :: OS Independent
Requires-Python: >=3.8
Requires-Dist: beautifulsoup4
Requires-Dist: lxml
Requires-Dist: python-pptx
Requires-Dist: playwright
Requires-Dist: nest_asyncio
Requires-Dist: requests
